Metadata-Version: 1.2
Name: wolframalpha-asyncio
Version: 4.0.1
Summary: Wolfram|Alpha 2.0 API Async client
Home-page: https://github.com/painor/wolframalpha-asyncio
Author: Painor
Author-email: topcode.softwares@gmail.com
License: UNKNOWN
Platform: UNKNOWN
Classifier: Development Status :: 5 - Production/Stable
Classifier: Intended Audience :: Developers
Classifier: License :: OSI Approved :: MIT License
Classifier: Programming Language :: Python :: 3
Requires-Python: >=3.5.3
